{
  "$schema": "https://developer.microsoft.com/json-schemas/fabric/item/report/definition/visualContainer/2.5.0/schema.json",
  "name": "2a5a8df46671c60af123",
  "position": {
    "x": 202,
    "y": 7,
    "z": 3000,
    "height": 37,
    "width": 138,
    "tabOrder": 3000
  },
  "visual": {
    "visualType": "card",
    "query": {
      "queryState": {
        "Values": {
          "projections": [
            {
              "field": {
                "Measure": {
                  "Expression": {
                    "SourceRef": {
                      "Entity": "*Measures"
                    }
                  },
                  "Property": "M_Cost Of Goods"
                }
              },
              "queryRef": "*Measures.M_Cost Of Goods",
              "displayName": "Cost Of Goods"
            }
          ]
        }
      },
      "sortDefinition": {
        "sort": [
          {
            "field": {
              "Measure": {
                "Expression": {
                  "SourceRef": {
                    "Entity": "*Measures"
                  }
                },
                "Property": "M_Cost Of Goods"
              }
            },
            "direction": "Descending"
          }
        ],
        "isDefaultSort": true
      }
    },
    "objects": {
      "labels": [
        {
          "properties": {
            "bold": {
              "expr": {
                "Literal": {
                  "Value": "true"
                }
              }
            },
            "labelDisplayUnits": {
              "expr": {
                "Literal": {
                  "Value": "1D"
                }
              }
            }
          }
        }
      ],
      "categoryLabels": [
        {
          "properties": {
            "color": {
              "solid": {
                "color": {
                  "expr": {
                    "ThemeDataColor": {
                      "ColorId": 3,
                      "Percent": 0
                    }
                  }
                }
              }
            },
            "show": {
              "expr": {
                "Literal": {
                  "Value": "false"
                }
              }
            }
          }
        }
      ]
    },
    "visualContainerObjects": {
      "background": [
        {
          "properties": {
            "show": {
              "expr": {
                "Literal": {
                  "Value": "false"
                }
              }
            }
          }
        }
      ],
      "title": [
        {
          "properties": {
            "text": {
              "expr": {
                "Literal": {
                  "Value": "'Card_COG'"
                }
              }
            }
          }
        }
      ]
    },
    "drillFilterOtherVisuals": true
  },
  "filterConfig": {
    "filters": [
      {
        "name": "Filterb1d37834b3a050c639b3",
        "field": {
          "Measure": {
            "Expression": {
              "SourceRef": {
                "Entity": "*Measures"
              }
            },
            "Property": "M_Cost Of Goods"
          }
        },
        "type": "Advanced",
        "isHiddenInViewMode": true
      }
    ]
  }
}