{
  "$schema": "https://developer.microsoft.com/json-schemas/fabric/item/report/definition/visualContainer/2.5.0/schema.json",
  "name": "856aa557f56da9af06e8",
  "position": {
    "x": 58.420046775810221,
    "y": 9.5008352823253972,
    "z": 6000,
    "height": 21.951219512195124,
    "width": 21.951219512195124,
    "tabOrder": 2000
  },
  "visual": {
    "visualType": "actionButton",
    "objects": {
      "icon": [
        {
          "properties": {
            "shapeType": {
              "expr": {
                "Literal": {
                  "Value": "'blank'"
                }
              }
            }
          },
          "selector": {
            "id": "default"
          }
        },
        {
          "properties": {
            "show": {
              "expr": {
                "Literal": {
                  "Value": "false"
                }
              }
            }
          }
        }
      ],
      "outline": [
        {
          "properties": {
            "show": {
              "expr": {
                "Literal": {
                  "Value": "false"
                }
              }
            }
          }
        }
      ],
      "fill": [
        {
          "properties": {
            "show": {
              "expr": {
                "Literal": {
                  "Value": "true"
                }
              }
            }
          }
        },
        {
          "properties": {
            "transparency": {
              "expr": {
                "Literal": {
                  "Value": "50D"
                }
              }
            },
            "image": {
              "image": {
                "name": {
                  "expr": {
                    "Literal": {
                      "Value": "'ICO_Twitter_White.svg'"
                    }
                  }
                },
                "url": {
                  "expr": {
                    "ResourcePackageItem": {
                      "PackageName": "RegisteredResources",
                      "PackageType": 1,
                      "ItemName": "ICO_Twitter_White12947263587504665.svg"
                    }
                  }
                },
                "scaling": {
                  "expr": {
                    "Literal": {
                      "Value": "'Normal'"
                    }
                  }
                }
              }
            },
            "fillColor": {
              "solid": {
                "color": {
                  "expr": {
                    "Measure": {
                      "Expression": {
                        "SourceRef": {
                          "Entity": "*Measures"
                        }
                      },
                      "Property": "M_Transparent"
                    }
                  }
                }
              }
            }
          },
          "selector": {
            "id": "default"
          }
        },
        {
          "properties": {
            "image": {
              "image": {
                "name": {
                  "expr": {
                    "Literal": {
                      "Value": "'ICO_Twitter_White.svg'"
                    }
                  }
                },
                "url": {
                  "expr": {
                    "ResourcePackageItem": {
                      "PackageName": "RegisteredResources",
                      "PackageType": 1,
                      "ItemName": "ICO_Twitter_White2153387267104372.svg"
                    }
                  }
                },
                "scaling": {
                  "expr": {
                    "Literal": {
                      "Value": "'Normal'"
                    }
                  }
                }
              }
            },
            "transparency": {
              "expr": {
                "Literal": {
                  "Value": "0D"
                }
              }
            }
          },
          "selector": {
            "id": "hover"
          }
        }
      ]
    },
    "visualContainerObjects": {
      "title": [
        {
          "properties": {
            "text": {
              "expr": {
                "Literal": {
                  "Value": "'Button_Twitter'"
                }
              }
            }
          }
        }
      ],
      "visualLink": [
        {
          "properties": {
            "show": {
              "expr": {
                "Literal": {
                  "Value": "false"
                }
              }
            },
            "type": {
              "expr": {
                "Literal": {
                  "Value": "'Bookmark'"
                }
              }
            },
            "bookmark": {
              "expr": {
                "Literal": {
                  "Value": "'Bookmarka4e95b9004952389e320'"
                }
              }
            }
          }
        }
      ]
    },
    "drillFilterOtherVisuals": true
  },
  "parentGroupName": "8cebc581efab06c8766a"
}